nti/__init__.py
nti/mailer/__init__.py
nti/mailer/_compat.py
nti/mailer/_default_template_mailer.py
nti/mailer/_verp.py
nti/mailer/configure.zcml
nti/mailer/interfaces.py
nti/mailer/queue.py
nti/mailer/tests/__init__.py
nti/mailer/tests/test_default_template_mailer.py
nti/mailer/tests/test_interfaces.py
nti/mailer/tests/test_queue.py
nti/mailer/tests/test_verp.py
nti/mailer/tests/templates/__init__.py
nti/mailer/tests/templates/test_new_user_created.mak
nti/mailer/tests/templates/test_new_user_created.pt
nti/mailer/tests/templates/test_new_user_created.txt
nti.mailer-1.0.0.dist-info/AUTHORS
nti.mailer-1.0.0.dist-info/LICENSE
nti.mailer-1.0.0.dist-info/METADATA
nti.mailer-1.0.0.dist-info/WHEEL
nti.mailer-1.0.0.dist-info/entry_points.txt
nti.mailer-1.0.0.dist-info/top_level.txt
nti.mailer-1.0.0.dist-info/zip-safe
nti.mailer-1.0.0.dist-info/RECORD
